flask_caching/__init__.py
flask_caching/jinja2ext.py
flask_caching/py.typed
flask_caching/utils.py
flask_caching/backends/__init__.py
flask_caching/backends/base.py
flask_caching/backends/filesystemcache.py
flask_caching/backends/memcache.py
flask_caching/backends/nullcache.py
flask_caching/backends/rediscache.py
flask_caching/backends/simplecache.py
flask_caching/backends/uwsgicache.py
flask_caching/contrib/__init__.py
flask_caching/contrib/googlecloudstoragecache.py
flask_caching/contrib/uwsgicache.py
Flask_Caching-2.2.0.dist-info/LICENSE
Flask_Caching-2.2.0.dist-info/METADATA
Flask_Caching-2.2.0.dist-info/WHEEL
Flask_Caching-2.2.0.dist-info/top_level.txt
Flask_Caching-2.2.0.dist-info/RECORD
