Metadata-Version: 2.1
Name: Flask-Caching
Version: 2.2.0
Summary: Adds caching support to Flask applications.
Home-page: https://github.com/pallets-eco/flask-caching
Author: Peter Justin
Author-email: peter.justin@outlook.com
Maintainer: Pallets
Maintainer-email: contact@palletsprojects.com
License: BSD
Project-URL: Donate, https://palletsprojects.com/donate
Project-URL: Documentation, https://flask-caching.readthedocs.io
Project-URL: Changes, https://flask-caching.readthedocs.io/en/latest/changelog.html
Project-URL: Source Code, https://github.com/pallets-eco/flask-caching
Project-URL: Issue Tracker, https://github.com/pallets-eco/flask-caching/issues
Project-URL: Twitter, https://twitter.com/PalletsTeam
Project-URL: Chat, https://discord.gg/pallets
Classifier: Development Status :: 5 - Production/Stable
Classifier: Intended Audience :: Developers
Classifier: License :: OSI Approved :: BSD License
Classifier: Operating System :: OS Independent
Classifier: Programming Language :: Python
Requires-Python: >=3.8
License-File: LICENSE
Requires-Dist: cachelib<0.10.0,>=0.9.0
Requires-Dist: Flask
